MANIFEST.in
README.rst
setup.py
backupallthethings/__init__.py
backupallthethings.egg-info/PKG-INFO
backupallthethings.egg-info/SOURCES.txt
backupallthethings.egg-info/dependency_links.txt
backupallthethings.egg-info/requires.txt
backupallthethings.egg-info/top_level.txt
bin/batt
conf/backup-couchdb.conf.template
conf/backup-file.conf.template
conf/backup-mongodb.conf.template
conf/backup-mysql.conf.template
conf/backup-postgresql.conf.template
conf/backup-redis.conf.template
conf/backup.conf.template
scripts-available/backup-couchdb
scripts-available/backup-file
scripts-available/backup-mongodb
scripts-available/backup-mysql
scripts-available/backup-postgresql
scripts-available/backup-redis