Metadata-Version: 1.0
Name: backupallthethings
Version: 0.0.5
Summary: Batt simply backup all the things; databases and files
Home-page: https://github.com/devo-ps/backupallthethings
Author: Vincent Viallet
Author-email: vincent@devo.ps
License: MIT
Platform: UNKNOWN
